<?xml version="1.0" encoding="utf-8" ?>
<EnemyTemplate VerticalAlignment="Bottom" RenderMode="Movement" Offense="2" Defense="2">
	<Size Width="30" Height="42" />
	<StartVelocity X="1" Y="0" />
	<Left IsSolid="false" />
	<Top IsSolid="false" />
	<Right IsSolid="false" />
	<Bottom IsSolid="false" />
	<MovementProvider Name="RunAndJump" MaxHorizontalSpeed="2.5" IntelligenceAlgorithm="TurnOnHoleOrCollision" DeathDuration="600" />
	<ShootInformation Duration="60" MinWait="120" MaxWait="120" FlipOnNegativeX="true" FlipOnNegativeY="false">
		<Object Path="Enemy/Fast_Right" MaxCount="10" />
		<StartPosition X="17" Y="15" />
		<StartVelocity X="2.5" Y="-7" />
	</ShootInformation>
</EnemyTemplate>
